{
  "EnLink": {
    "region": "Korea",
    "url": "https://rosa-iot.org",
    "logo": "https://rosa-iot.org/branding.png",
    "darkLogo": "https://rosa-iot.org/branding_dark.png",
    "frequencyPlan": "KR920/KR920-923",
    "status":"online"
  },
  "XY Pool": {
    "region": "China",
    "url": "https://mxcxy.com",
    "logo": "https://mxcxy.com/branding.png",
    "darkLogo": "https://mxcxy.com/branding_dark.png",
    "frequencyPlan": "CN470/CN470-510",
    "status":"online"
  },
  "MatchX": {
    "region": "Europe",
    "url": "https://eusn.matchx.io",
    "logo": "https://eusn.matchx.io/branding.png",
    "darkLogo": "https://eusn.matchx.io/branding_dark.png",
    "frequencyPlan": "EU868/EU863-870",
    "status": "online"
  },
  "DU IoT": {
    "region": "Asia",
    "url": "https://duiot.net",
    "logo": "https://duiot.net/branding.png",
    "darkLogo": "https://duiot.net/branding_dark.png",
    "frequencyPlan": "AS923/AS923-1",
    "status":"online"
  },
  "Huobi Pool": {
    "region": "America",
    "url": "https://ussn.matchx.io",
    "logo": "https://ussn.matchx.io/branding.png",
    "darkLogo": "https://ussn.matchx.io/branding_dark.png",
    "frequencyPlan": "US915/US902-928",
    "status":"online"
  },
  "Sejong Solutech": {
    "region": "Korea",
    "url": "https://k-supernode.com",
    "logo": "https://k-supernode.com/branding.png",
    "darkLogo": "https://k-supernode.com/branding_dark.png",
    "frequencyPlan": "KR920/KR920-923",
    "status":"online"
  },
  "MXCtest": {
    "region": "Test",
    "url": "https://lora.test.cloud.mxc.org",
    "logo": "https://lora.test.cloud.mxc.org/branding.png",
    "darkLogo": "https://lora.test.cloud.mxc.org/branding_dark.png",
    "frequencyPlan": "Frequency MXCtest",
    "status":"online"
  },
  "MXCbuild": {
    "region": "Test",
    "url": "https://lora.build.cloud.mxc.org",
    "logo": "https://lora.build.cloud.mxc.org/branding.png",
    "darkLogo": "https://lora.build.cloud.mxc.org/branding_dark.png",
    "frequencyPlan": "Frequency MXCbuild",
    "status":"online",
    "captchaDisabled":true
  },
  "MXCbuild2": {
    "region": "Test",
    "url": "https://build2.cloud.mxc.org",
    "logo": "https://build2.cloud.mxc.org/branding.png",
    "darkLogo": "https://build2.cloud.mxc.org/branding_dark.png",
    "frequencyPlan": "Frequency MXCbuild2",
    "status":"online"
    "captchaDisabled":true
  },
  "MXCbuild3": {
    "region": "Test",
    "url": "https://build3.cloud.mxc.org",
    "logo": "https://build3.cloud.mxc.org/branding.png",
    "darkLogo": "https://build3.cloud.mxc.org/branding_dark.png",
    "frequencyPlan": "Frequency MXCbuild3",
    "status":"online"
  },
  "MXCChina": {
    "region": "Test",
    "url": "https://test.china.mxc.org",
    "logo": "https://test.china.mxc.org/branding.png",
    "darkLogo": "https://test.china.mxc.org/branding_dark.png",
    "frequencyPlan": "Frequency MXCChina",
    "status":"online"
  },
  "Wanshi Pool": {
    "region": "China",
    "url": "https://wanshipool.com",
    "logo": "https://wanshipool.com/branding.png",
    "darkLogo": "https://wanshipool.com/branding_dark.png",
    "frequencyPlan": "CN470/CN470-510",
    "status":"online"
  }
}
